{"db_redis-basic.md":"17d1c1c9","geektime_early-code.md":"494237d4","index.md":"8aef1656","deploy_gitee-pipeline.md":"99627307","deploy_github-vite-press.md":"cd6a1b29","geektime_tdd-project-70-course.md":"2fe5f597","other_web-security.md":"e77ef7fc","other_data-analysis-start.md":"bf0202bc","vite-press_how-use-third-party-components.md":"820d2b15","vite-press_carousel.md":"b0eb1890","vite-press_index.md":"c9f5d5c9","other_message-queue-basic.md":"e4a4cef1","mongo_get-started.md":"aef2aa0a","other_design-patterns.md":"f2513647","db_mysql-get-started.md":"ffea99bc","other_crypto-aes-encrypt.md":"dab9b877","geektime_modernization-of-legacy-systems.md":"a713b2ce"}
